simplemagic/__init__.py
simplemagic/cli.py
simplemagic/extra_mimetypes.py
simplemagic/fixmagic.py
simplemagic/fixpuremagic.py
simplemagic/magic.py
simplemagic/utils.py
simplemagic-0.1.12.dist-info/licenses/LICENSE
simplemagic-0.1.12.dist-info/METADATA
simplemagic-0.1.12.dist-info/WHEEL
simplemagic-0.1.12.dist-info/entry_points.txt
simplemagic-0.1.12.dist-info/top_level.txt
simplemagic-0.1.12.dist-info/RECORD
