Metadata-Version: 2.4
Name: simplemagic
Version: 0.1.12
Summary: Simple file magic. We try to get file's mimetype using 'file-magic', 'command file' and 'puremagic'. On linux we need system package 'file-libs' which mostly already installed. On MacOS we need system package 'libimage' which can be installed by 'brew install libmagic'. On windows we need file command which can be install by 'pacman -S file' within msys2. If system package missing, we try to get the file's mimetype using 'puremagic' which is write in pure python without any extra depend
Author: rRR0VrFP
Maintainer: rRR0VrFP
License: MIT
Keywords: libmagic,file-magic,file
Classifier: Development Status :: 5 - Production/Stable
Classifier: Intended Audience :: Developers
Classifier: Topic :: Software Development :: Libraries :: Python Modules
Classifier: Programming Language :: Python :: 3
Classifier: Programming Language :: Python :: 3 :: Only
License-File: LICENSE
Requires-Dist: file-magic
Requires-Dist: puremagic
Requires-Dist: binaryornot
Requires-Dist: click
Dynamic: author
Dynamic: classifier
Dynamic: description
Dynamic: description-content-type
Dynamic: keywords
Dynamic: license
Dynamic: license-file
Dynamic: maintainer
Dynamic: requires-dist
Dynamic: summary
